{
  "PRESETS":{
    "C69" :{
      "Options" : {
        "Body" : "Cylinder",
        "Top" : "Cone",
        "Neck Position" : "Center",
        "Door" : "Inside",
        "Door Shape" : "Ellipse"
      },
      "Values" : {
        "Base Diameter" : 304.5,
        "Total Height" : 553.0165,
        "Neck Diameter" : 40,
        "Neck Height" : 36,
        "Hypotenuse" : 136,
        "Door Depht" : 1.5,
        "Door Bigger Diameter" : 43,
        "Door Smaller Diameter" : 31
      }
    }
  }


}